sms_message_inforu_local/__init__.py
sms_message_inforu_local/sms_message_inforu.py
sms_message_inforu_local-0.0.5.dist-info/METADATA
sms_message_inforu_local-0.0.5.dist-info/WHEEL
sms_message_inforu_local-0.0.5.dist-info/top_level.txt
sms_message_inforu_local-0.0.5.dist-info/RECORD
